mykefiles/__init__.py
mykefiles/__version__.py
mykefiles/hello_world.py
mykefiles/py.typed
mykefiles/py_pkg.py
mykefiles/__pycache__/__init__.cpython-310.pyc
mykefiles/__pycache__/__init__.cpython-311.pyc
mykefiles/__pycache__/__init__.cpython-37.pyc
mykefiles/__pycache__/__init__.cpython-38.pyc
mykefiles/__pycache__/__init__.cpython-39.pyc
mykefiles/__pycache__/__main__.cpython-37.pyc
mykefiles/__pycache__/__version__.cpython-310.pyc
mykefiles/__pycache__/__version__.cpython-311.pyc
mykefiles/__pycache__/__version__.cpython-37.pyc
mykefiles/__pycache__/__version__.cpython-38.pyc
mykefiles/__pycache__/__version__.cpython-39.pyc
mykefiles/__pycache__/hello_world.cpython-310.pyc
mykefiles/__pycache__/hello_world.cpython-311.pyc
mykefiles/__pycache__/hello_world.cpython-37.pyc
mykefiles/__pycache__/hello_world.cpython-38.pyc
mykefiles/__pycache__/hello_world.cpython-39.pyc
mykefiles/__pycache__/hostbutter.cpython-310.pyc
mykefiles/__pycache__/hostbutter.cpython-311.pyc
mykefiles/__pycache__/hostbutter.cpython-37.pyc
mykefiles/__pycache__/hostbutter.cpython-38.pyc
mykefiles/__pycache__/hostbutter.cpython-39.pyc
mykefiles/__pycache__/py_pkg.cpython-310.pyc
mykefiles/__pycache__/py_pkg.cpython-311.pyc
mykefiles/__pycache__/py_pkg.cpython-37.pyc
mykefiles/__pycache__/py_pkg.cpython-38.pyc
mykefiles/__pycache__/py_pkg.cpython-39.pyc
mykefiles-0.0.1a3.dev8.dist-info/LICENSE
mykefiles-0.0.1a3.dev8.dist-info/METADATA
mykefiles-0.0.1a3.dev8.dist-info/WHEEL
mykefiles-0.0.1a3.dev8.dist-info/top_level.txt
mykefiles-0.0.1a3.dev8.dist-info/RECORD
