Metadata-Version: 2.1
Name: mykefiles
Version: 0.0.1a3.dev8
Summary: WIP
Home-page: https://www.github.com/fresh2dev/mykefiles
Author: Donald Mellenbruch
Author-email: hello@Fresh2.dev
Project-URL: Homepage, https://www.Fresh2.dev/code/r/mykefiles/i
Project-URL: Repository, https://www.github.com/fresh2dev/mykefiles
Project-URL: Funding, https://www.Fresh2.dev/funding
Classifier: Programming Language :: Python :: 3
Requires-Python: >=3.7
License-File: LICENSE
Requires-Dist: typing-extensions ; python_version < "3.10"
Provides-Extra: build
Requires-Dist: setuptools (>=62.3.0) ; extra == 'build'
Requires-Dist: build (==0.*) ; extra == 'build'
Requires-Dist: wheel (==0.*) ; extra == 'build'
Requires-Dist: twine (==4.*) ; extra == 'build'
Provides-Extra: dev
Requires-Dist: python-lsp-server[rope] (==1.*) ; extra == 'dev'
Requires-Dist: pylint (==2.*) ; extra == 'dev'
Requires-Dist: pylint-pytest (==1.*) ; extra == 'dev'
Requires-Dist: mypy[reports] (==0.*) ; extra == 'dev'
Requires-Dist: ruff (==0.*) ; extra == 'dev'
Requires-Dist: black (==23.*) ; extra == 'dev'
Requires-Dist: isort (==5.*) ; extra == 'dev'
Requires-Dist: bump2version (==1.*) ; extra == 'dev'
Requires-Dist: ipython ; extra == 'dev'
Requires-Dist: pdbpp ; extra == 'dev'
Provides-Extra: docs
Requires-Dist: mkdocs (==1.*) ; extra == 'docs'
Requires-Dist: mkdocs-material (==9.*) ; extra == 'docs'
Requires-Dist: mkdocstrings[python] (==0.20.*) ; extra == 'docs'
Requires-Dist: mkdocs-autorefs (==0.*) ; extra == 'docs'
Requires-Dist: mkdocs-include-dir-to-nav (==1.*) ; extra == 'docs'
Provides-Extra: myke
Requires-Dist: myke[extras] (==0.0.1a23) ; extra == 'myke'
Provides-Extra: tests
Requires-Dist: pytest (==7.*) ; extra == 'tests'
Requires-Dist: pytest-cov (==4.*) ; extra == 'tests'
Requires-Dist: pytest-html (==3.*) ; extra == 'tests'
Requires-Dist: pytest-sugar (==0.*) ; extra == 'tests'
Requires-Dist: pytest-custom-exit-code (==0.3.*) ; extra == 'tests'
Requires-Dist: pylint (==2.*) ; extra == 'tests'
Requires-Dist: pylint-pytest (==1.*) ; extra == 'tests'
Requires-Dist: packaging (==23.*) ; extra == 'tests'
Requires-Dist: myke[extras] (==0.0.1a23) ; extra == 'tests'
